markitdown_mcp_server/__init__.py
markitdown_mcp_server/server.py
iflow_mcp_markitdown_mcp_server-0.1.0.dist-info/METADATA
iflow_mcp_markitdown_mcp_server-0.1.0.dist-info/WHEEL
iflow_mcp_markitdown_mcp_server-0.1.0.dist-info/entry_points.txt
iflow_mcp_markitdown_mcp_server-0.1.0.dist-info/licenses/LICENSE
iflow_mcp_markitdown_mcp_server-0.1.0.dist-info/RECORD
