Metadata-Version: 2.4
Name: iflow-mcp_markitdown-mcp-server
Version: 0.1.0
Summary: Add your description here
Author-email: korigamik-hypr <korigamik@gmail.com>
License-File: LICENSE
Requires-Python: >=3.12
Requires-Dist: markitdown>=0.1
Requires-Dist: mcp>=1.2.1
